{
  "symbol": "btcusdt",
  "timeframe": "1m",
  "candle": {
    "startTime": 1783332720000,
    "open": 62817.46,
    "high": 62832.6,
    "low": 62817.45,
    "close": 62832.6,
    "volume": 704,
    "direction": "up",
    "volatility": 15.150000000001455,
    "totalVolume": 704
  },
  "trades": {
    "count": 2095,
    "buyVolume": 4.213360000000026,
    "sellVolume": 10.376740000000025,
    "bigTrades": []
  },
  "depthImportant": {
    "buys": [
      {
        "side": "buy",
        "layer": 1,
        "price": 62832.59,
        "qty": 5.18332,
        "cumulative": 5.18332
      },
      {
        "side": "buy",
        "layer": 30,
        "price": 62827.86,
        "qty": 0.25639,
        "cumulative": 6.87868
      },
      {
        "side": "buy",
        "layer": 34,
        "price": 62826.86,
        "qty": 0.53256,
        "cumulative": 5.71588
      },
      {
        "side": "buy",
        "layer": 38,
        "price": 62826.5,
        "qty": 0.383,
        "cumulative": 6.6222900000000005
      },
      {
        "side": "buy",
        "layer": 48,
        "price": 62825.07,
        "qty": 0.52341,
        "cumulative": 6.2392900000000004
      },
      {
        "side": "buy",
        "layer": 54,
        "price": 62824.53,
        "qty": 0.70668,
        "cumulative": 12.369570000000001
      },
      {
        "side": "buy",
        "layer": 65,
        "price": 62823.35,
        "qty": 0.57361,
        "cumulative": 13.516810000000001
      },
      {
        "side": "buy",
        "layer": 85,
        "price": 62820.43,
        "qty": 0.57363,
        "cumulative": 12.943200000000001
      },
      {
        "side": "buy",
        "layer": 95,
        "price": 62818.24,
        "qty": 1.60115,
        "cumulative": 11.66289
      },
      {
        "side": "buy",
        "layer": 96,
        "price": 62818.23,
        "qty": 3.18306,
        "cumulative": 10.06174
      },
      {
        "side": "buy",
        "layer": 163,
        "price": 62809.17,
        "qty": 1.33799,
        "cumulative": 22.722340000000006
      },
      {
        "side": "buy",
        "layer": 168,
        "price": 62807.53,
        "qty": 3.18382,
        "cumulative": 16.70063
      },
      {
        "side": "buy",
        "layer": 175,
        "price": 62806.01,
        "qty": 1.50089,
        "cumulative": 21.384350000000005
      },
      {
        "side": "buy",
        "layer": 178,
        "price": 62805.85,
        "qty": 1.57786,
        "cumulative": 19.883460000000003
      },
      {
        "side": "buy",
        "layer": 179,
        "price": 62805.19,
        "qty": 1.60497,
        "cumulative": 18.305600000000002
      },
      {
        "side": "buy",
        "layer": 388,
        "price": 62681.43,
        "qty": 6.47808,
        "cumulative": 733.2731699999999
      },
      {
        "side": "buy",
        "layer": 447,
        "price": 62500,
        "qty": 18.62578,
        "cumulative": 726.79509
      },
      {
        "side": "buy",
        "layer": 473,
        "price": 62000,
        "qty": 29.89748,
        "cumulative": 708.16931
      },
      {
        "side": "buy",
        "layer": 484,
        "price": 61500,
        "qty": 35.73437,
        "cumulative": 678.27183
      },
      {
        "side": "buy",
        "layer": 497,
        "price": 60000,
        "qty": 619.81512,
        "cumulative": 642.53746
      },
      {
        "side": "buy",
        "layer": 509,
        "price": 58000,
        "qty": 109.78407,
        "cumulative": 1936.88639
      },
      {
        "side": "buy",
        "layer": 511,
        "price": 57000,
        "qty": 254.17325,
        "cumulative": 1573.06269
      },
      {
        "side": "buy",
        "layer": 528,
        "price": 55000,
        "qty": 585.61627,
        "cumulative": 1318.88944
      },
      {
        "side": "buy",
        "layer": 529,
        "price": 53500,
        "qty": 105.74934,
        "cumulative": 2042.63573
      },
      {
        "side": "buy",
        "layer": 540,
        "price": 40000,
        "qty": 254.03963,
        "cumulative": 1827.10232
      }
    ],
    "sells": [
      {
        "side": "sell",
        "layer": 1,
        "price": 62832.6,
        "qty": 1.64352,
        "cumulative": 1.64352
      },
      {
        "side": "sell",
        "layer": 5,
        "price": 62833.18,
        "qty": 0.11168,
        "cumulative": 3.66814
      },
      {
        "side": "sell",
        "layer": 30,
        "price": 62837.97,
        "qty": 0.14021,
        "cumulative": 3.5564600000000004
      },
      {
        "side": "sell",
        "layer": 33,
        "price": 62838.07,
        "qty": 1.29653,
        "cumulative": 2.9400500000000003
      },
      {
        "side": "sell",
        "layer": 34,
        "price": 62838.08,
        "qty": 0.4762,
        "cumulative": 3.4162500000000002
      },
      {
        "side": "sell",
        "layer": 52,
        "price": 62840.6,
        "qty": 3.18306,
        "cumulative": 10.41717
      },
      {
        "side": "sell",
        "layer": 73,
        "price": 62844.37,
        "qty": 0.4762,
        "cumulative": 13.610470000000001
      },
      {
        "side": "sell",
        "layer": 74,
        "price": 62844.38,
        "qty": 1.24004,
        "cumulative": 13.13427
      },
      {
        "side": "sell",
        "layer": 75,
        "price": 62844.39,
        "qty": 3.56597,
        "cumulative": 7.23411
      },
      {
        "side": "sell",
        "layer": 95,
        "price": 62847.43,
        "qty": 1.47706,
        "cumulative": 11.89423
      },
      {
        "side": "sell",
        "layer": 108,
        "price": 62848.9,
        "qty": 3.18306,
        "cumulative": 20.3595
      },
      {
        "side": "sell",
        "layer": 125,
        "price": 62852.96,
        "qty": 3.18306,
        "cumulative": 23.54256
      },
      {
        "side": "sell",
        "layer": 144,
        "price": 62856.8,
        "qty": 1.6166,
        "cumulative": 28.342220000000005
      },
      {
        "side": "sell",
        "layer": 145,
        "price": 62856.81,
        "qty": 3.56597,
        "cumulative": 17.17644
      },
      {
        "side": "sell",
        "layer": 181,
        "price": 62864.35,
        "qty": 3.18306,
        "cumulative": 26.725620000000003
      },
      {
        "side": "sell",
        "layer": 272,
        "price": 62899.93,
        "qty": 4.77426,
        "cumulative": 96.29267
      },
      {
        "side": "sell",
        "layer": 335,
        "price": 62950.02,
        "qty": 4.77047,
        "cumulative": 101.06314
      },
      {
        "side": "sell",
        "layer": 336,
        "price": 62950.66,
        "qty": 4.77042,
        "cumulative": 105.83356
      },
      {
        "side": "sell",
        "layer": 344,
        "price": 62957.31,
        "qty": 4.76991,
        "cumulative": 110.60347
      },
      {
        "side": "sell",
        "layer": 395,
        "price": 64000,
        "qty": 63.17619,
        "cumulative": 91.51841
      }
    ]
  },
  "updatedAt": 1783332780714
}